pem/__init__.py
pem/__main__.py
pem/cli.py
pem/config.py
pem/settings.py
pem/commands/__init__.py
pem/commands/config.py
pem/core/__init__.py
pem/core/executor.py
pem/core/scheduler.py
pem/db/__init__.py
pem/db/database.py
pem/db/models.py
pemexe-1.5.1.dist-info/METADATA
pemexe-1.5.1.dist-info/WHEEL
pemexe-1.5.1.dist-info/entry_points.txt
pemexe-1.5.1.dist-info/licenses/LICENSE
pemexe-1.5.1.dist-info/RECORD
