Metadata-Version: 2.4
Name: pemexe
Version: 1.5.1
Summary: 🚀 Python Execution Manager - A powerful, modern tool for managing, scheduling, and executing Python scripts and projects with comprehensive logging, flexible scheduling, and dependency management. Perfect for DevOps, data science, and automation workflows.
Project-URL: Homepage, https://github.com/arian24b/pem
Project-URL: Repository, https://github.com/arian24b/pem.git
Project-URL: Issues, https://github.com/arian24b/pem/issues
Project-URL: Changelog, https://github.com/arian24b/pem/blob/main/CHANGELOG.md
Project-URL: Documentation, https://github.com/arian24b/pem#readme
Author-email: Arian Omrani <arian24b@gmail.com>
Maintainer-email: Arian Omrani <arian24b@gmail.com>
License: MIT License
License-File: LICENSE
Keywords: automation,background-jobs,cli,cron,dependencies,devops,execution,logging,management,projects,python,scheduler,scripts,task-runner
Classifier: Development Status :: 4 - Beta
Classifier: Environment :: Console
Classifier: Intended Audience :: Developers
Classifier: Intended Audience :: System Administrators
Classifier: License :: OSI Approved :: MIT License
Classifier: Operating System :: OS Independent
Classifier: Programming Language :: Python :: 3
Classifier: Programming Language :: Python :: 3.13
Classifier: Programming Language :: Python :: 3.14
Classifier: Topic :: Software Development :: Libraries :: Python Modules
Classifier: Topic :: System :: Systems Administration
Classifier: Topic :: Utilities
Classifier: Typing :: Typed
Requires-Python: >=3.13
Requires-Dist: aiosqlite>=0.21.0
Requires-Dist: apscheduler>=3.11.0
Requires-Dist: faker>=37.5.3
Requires-Dist: greenlet>=3.2.3
Requires-Dist: platformdirs>=4.3.6
Requires-Dist: psutil>=6.1.0
Requires-Dist: pydantic>=2.10.0
Requires-Dist: sqlalchemy>=2.0.41
Requires-Dist: typer>=0.16.0
